README.rst
setup.py
WikiEnte.egg-info/PKG-INFO
WikiEnte.egg-info/SOURCES.txt
WikiEnte.egg-info/dependency_links.txt
WikiEnte.egg-info/entry_points.txt
WikiEnte.egg-info/not-zip-safe
WikiEnte.egg-info/requires.txt
WikiEnte.egg-info/top_level.txt
wikiente/__init__.py
wikiente/wikiente.py